tcr/__init__.py
tcr/convert.py
tcr/datadir.py
tcr/iodata.py
tcr/parameters.py
tcr/physics.py
tcr/plots.py
tcr/rainfall.py
tcr/terrain_boundary.py
tcr/wind.py
tcr/data/surface_data.nc
tcr/data/colormaps/BlueWhiteOrangeRed.cpt
tcr/data/colormaps/precip2_17lev.cpt
tcr/data/downscaled/historical/tracks_NA_E3SM-1-0_historical_r1i1p1f1_196401_201412.nc
tcr/data/downscaled/historical/tracks_NA_REANALYSIS_historical_r1i1p1f1_196401_201412.nc
tcr/data/observations/IBTrACS.NA.v04r00.nc
tcr/data/shapefiles/CONUS.cpg
tcr/data/shapefiles/CONUS.dbf
tcr/data/shapefiles/CONUS.prj
tcr/data/shapefiles/CONUS.shp
tcr/data/shapefiles/CONUS.shx
tcr/data/shapefiles/Texas_bound.cpg
tcr/data/shapefiles/Texas_bound.dbf
tcr/data/shapefiles/Texas_bound.prj
tcr/data/shapefiles/Texas_bound.qmd
tcr/data/shapefiles/Texas_bound.shp
tcr/data/shapefiles/Texas_bound.shx
tcr/data/shapefiles/setx_bound.cpg
tcr/data/shapefiles/setx_bound.dbf
tcr/data/shapefiles/setx_bound.prj
tcr/data/shapefiles/setx_bound.qmd
tcr/data/shapefiles/setx_bound.shp
tcr/data/shapefiles/setx_bound.shx
pytcr-1.2.3.dist-info/METADATA
pytcr-1.2.3.dist-info/WHEEL
pytcr-1.2.3.dist-info/licenses/LICENSE
pytcr-1.2.3.dist-info/RECORD
