Metadata-Version: 2.4
Name: pyTCR
Version: 1.2.3
Summary: A model for tropical cyclone rainfall
Author-email: Phong Le <levuvietphong@gmail.com>
License-File: LICENSE
Classifier: License :: OSI Approved :: MIT License
Classifier: Operating System :: OS Independent
Classifier: Programming Language :: Python :: 3
Requires-Python: >=3.11
Requires-Dist: beautifulsoup4
Requires-Dist: cartopy
Requires-Dist: colorcet
Requires-Dist: geopandas
Requires-Dist: jupyter
Requires-Dist: matplotlib
Requires-Dist: netcdf4
Requires-Dist: numpy
Requires-Dist: pyproj
Requires-Dist: requests
Requires-Dist: scipy
Requires-Dist: shapely
Requires-Dist: xarray
